flink/__init__.py
flink/flink.py
flink_svector-0.5.9.dist-info/METADATA
flink_svector-0.5.9.dist-info/WHEEL
flink_svector-0.5.9.dist-info/entry_points.txt
flink_svector-0.5.9.dist-info/top_level.txt
flink_svector-0.5.9.dist-info/RECORD
