Metadata-Version: 2.4
Name: flink-svector
Version: 0.5.9
Summary: A distributed version control system for tracking changes in source code
Home-page: https://github.com/siddharth-coder8/flink
Author: Siddharth Shah
Author-email: team@svector.co.in
Classifier: Programming Language :: Python :: 3
Classifier: License :: OSI Approved :: MIT License
Classifier: Operating System :: OS Independent
Requires-Python: >=3.6
Requires-Dist: firebase-admin
Requires-Dist: tabulate
Dynamic: author
Dynamic: author-email
Dynamic: classifier
Dynamic: description-content-type
Dynamic: home-page
Dynamic: requires-dist
Dynamic: requires-python
Dynamic: summary
